az_data_generator-0.1.0.dist-info/licenses/LICENSE
data_generator/__init__.py
data_generator/generator.py
data_generator/data/azerbaijan_bins.json
data_generator/data/data.json
data_generator/modules/__init__.py
data_generator/modules/address_generator.py
data_generator/modules/card_generator.py
data_generator/modules/city_generator.py
data_generator/modules/date_generator.py
data_generator/modules/district_generator.py
data_generator/modules/email_generator.py
data_generator/modules/fin_generator.py
data_generator/modules/iban_generator.py
data_generator/modules/ip_generator.py
data_generator/modules/license_generator.py
data_generator/modules/name_generator.py
data_generator/modules/passport_generator.py
data_generator/modules/phone_generator.py
data_generator/modules/plate_generator.py
data_generator/modules/ssn_generator.py
data_generator/modules/street_generator.py
data_generator/modules/tax_id_generator.py
data_generator/modules/time_generator.py
data_generator/modules/town_generator.py
data_generator/modules/village_generator.py
data_generator/modules/zipcode_generator.py
az_data_generator-0.1.0.dist-info/METADATA
az_data_generator-0.1.0.dist-info/WHEEL
az_data_generator-0.1.0.dist-info/top_level.txt
az_data_generator-0.1.0.dist-info/RECORD
