Metadata-Version: 2.4
Name: az-data-generator
Version: 0.1.0
Summary: A comprehensive Python library for generating realistic test data for Azerbaijan, including personal identification, banking, geographical, and contact information. Designed for developers, testers, and data scientists who need high-quality, realistic test data that follows Azerbaijani formats and standards.
Home-page: https://github.com/LocalDoc-Azerbaijan/az-data-generator
Author: LocalDoc
Author-email: v.resad.89@gmail.com
Classifier: Programming Language :: Python :: 3
Classifier: License :: OSI Approved :: Apache Software License
Classifier: Operating System :: OS Independent
Requires-Python: >=3.6
License-File: LICENSE
Dynamic: author
Dynamic: author-email
Dynamic: classifier
Dynamic: description
Dynamic: description-content-type
Dynamic: home-page
Dynamic: license-file
Dynamic: requires-python
Dynamic: summary
